matrice_inference/__init__.py
matrice_inference/py.typed
matrice_inference/server/__init__.py
matrice_inference/server/inference_interface.py
matrice_inference/server/proxy_interface.py
matrice_inference/server/server.py
matrice_inference/server/model/__init__.py
matrice_inference/server/model/model_manager.py
matrice_inference/server/model/model_manager_wrapper.py
matrice_inference/server/model/triton_model_manager.py
matrice_inference/server/model/triton_server.py
matrice_inference/server/stream/DATA_FLOW_DIAGRAM.md
matrice_inference/server/stream/HIGH_THROUGHPUT_OPTIMIZATIONS.md
matrice_inference/server/stream/STREAMING_PIPELINE_ARCHITECTURE.md
matrice_inference/server/stream/__init__.py
matrice_inference/server/stream/analytics_publisher.py
matrice_inference/server/stream/app_deployment.py
matrice_inference/server/stream/app_event_listener.py
matrice_inference/server/stream/async_producer_pool.py
matrice_inference/server/stream/camera_config_monitor.py
matrice_inference/server/stream/consumer_manager.py
matrice_inference/server/stream/deployment_refresh_listener.py
matrice_inference/server/stream/frame_cache.py
matrice_inference/server/stream/inference_metric_logger.py
matrice_inference/server/stream/inference_worker.py
matrice_inference/server/stream/metric_publisher.py
matrice_inference/server/stream/post_processing_manager.py
matrice_inference/server/stream/producer_worker.py
matrice_inference/server/stream/stream_pipeline.py
matrice_inference/server/stream/utils.py
matrice_inference/server/stream/worker_metrics.py
matrice_inference/tmp/abstract_model_manager.py
matrice_inference/tmp/batch_manager.py
matrice_inference/tmp/overall_inference_testing.py
matrice_inference/tmp/triton_utils.py
matrice_inference/tmp/aggregator/__init__.py
matrice_inference/tmp/aggregator/aggregator.py
matrice_inference/tmp/aggregator/analytics.py
matrice_inference/tmp/aggregator/ingestor.py
matrice_inference/tmp/aggregator/latency.py
matrice_inference/tmp/aggregator/pipeline.py
matrice_inference-0.1.146.dist-info/licenses/LICENSE.txt
matrice_inference-0.1.146.dist-info/METADATA
matrice_inference-0.1.146.dist-info/WHEEL
matrice_inference-0.1.146.dist-info/top_level.txt
matrice_inference-0.1.146.dist-info/RECORD
